parallel_llm/__init__.py
parallel_llm/cli.py
parallel_llm/config.py
parallel_llm/diffusion_transformer.py
parallel_llm/parallel_generator.py
parallel_llm/trainer.py
parallel_llm-0.1.1.dist-info/METADATA
parallel_llm-0.1.1.dist-info/WHEEL
parallel_llm-0.1.1.dist-info/entry_points.txt
parallel_llm-0.1.1.dist-info/top_level.txt
parallel_llm-0.1.1.dist-info/RECORD
