Metadata-Version: 2.4
Name: parallel-llm
Version: 0.1.1
Summary: Ultra-fast parallel training and inference for language models
Author-email: Parallel-LLM Team <contact@parallel-llm.ai>
Maintainer-email: Furqan Khan <furqan@lastappstanding.com>
License-Expression: Apache-2.0
Project-URL: Homepage, https://github.com/furqan-y-khan/parallel-llm
Project-URL: Documentation, https://parallel-llm.readthedocs.io/
Project-URL: Repository, https://github.com/furqan-y-khan/parallel-llm
Project-URL: Issues, https://github.com/furqan-y-khan/parallel-llm/issues
Project-URL: Changelog, https://github.com/furqan-y-khan/parallel-llm/blob/main/CHANGELOG.md
Keywords: machine-learning,deep-learning,transformers,language-models,parallel-computing,distributed-training,diffusion-models,pytorch,cuda,gpu,llm,ai,nlp
Classifier: Development Status :: 4 - Beta
Classifier: Intended Audience :: Developers
Classifier: Intended Audience :: Science/Research
Classifier: Operating System :: OS Independent
Classifier: Programming Language :: Python
Classifier: Programming Language :: Python :: 3
Classifier: Programming Language :: Python :: 3.9
Classifier: Programming Language :: Python :: 3.10
Classifier: Programming Language :: Python :: 3.11
Classifier: Programming Language :: Python :: 3.12
Classifier: Topic :: Scientific/Engineering :: Artificial Intelligence
Classifier: Topic :: Software Development :: Libraries :: Python Modules
Requires-Python: >=3.9
Requires-Dist: torch>=2.2.0
Requires-Dist: transformers>=4.36.0
Requires-Dist: accelerate>=0.25.0
Requires-Dist: numpy>=1.24.0
Requires-Dist: einops>=0.7.0
Requires-Dist: tqdm>=4.66.0
Requires-Dist: safetensors>=0.4.0
Requires-Dist: huggingface-hub>=0.20.0
Provides-Extra: dev
Requires-Dist: pytest>=7.0; extra == "dev"
Requires-Dist: black>=23.0; extra == "dev"
Requires-Dist: flake8>=6.0; extra == "dev"
Requires-Dist: mypy>=1.0; extra == "dev"
Requires-Dist: isort>=5.12.0; extra == "dev"
Provides-Extra: docs
Requires-Dist: sphinx>=5.0; extra == "docs"
Requires-Dist: sphinx-rtd-theme>=1.0; extra == "docs"
Requires-Dist: myst-parser>=0.18.0; extra == "docs"
Provides-Extra: gpu
Requires-Dist: triton>=2.2.0; extra == "gpu"
Requires-Dist: flash-attn>=2.5.0; extra == "gpu"
Requires-Dist: xformers>=0.0.23; extra == "gpu"
Provides-Extra: distributed
Requires-Dist: deepspeed>=0.12.0; extra == "distributed"
Provides-Extra: multimodal
Requires-Dist: torchvision>=0.17.0; extra == "multimodal"
Requires-Dist: timm>=0.9.0; extra == "multimodal"
Requires-Dist: open-clip-torch>=2.24.0; extra == "multimodal"
Provides-Extra: inference
Requires-Dist: vllm>=0.3.0; extra == "inference"
Provides-Extra: logging
Requires-Dist: wandb>=0.16.0; extra == "logging"
Requires-Dist: tensorboard>=2.15.0; extra == "logging"
Provides-Extra: all
Requires-Dist: pytest>=7.0; extra == "all"
Requires-Dist: black>=23.0; extra == "all"
Requires-Dist: flake8>=6.0; extra == "all"
Requires-Dist: mypy>=1.0; extra == "all"
Requires-Dist: isort>=5.12.0; extra == "all"
Requires-Dist: sphinx>=5.0; extra == "all"
Requires-Dist: sphinx-rtd-theme>=1.0; extra == "all"
Requires-Dist: myst-parser>=0.18.0; extra == "all"
Requires-Dist: triton>=2.2.0; extra == "all"
Requires-Dist: flash-attn>=2.5.0; extra == "all"
Requires-Dist: xformers>=0.0.23; extra == "all"
Requires-Dist: deepspeed>=0.12.0; extra == "all"
Requires-Dist: torchvision>=0.17.0; extra == "all"
Requires-Dist: timm>=0.9.0; extra == "all"
Requires-Dist: open-clip-torch>=2.24.0; extra == "all"
Requires-Dist: vllm>=0.3.0; extra == "all"
Requires-Dist: wandb>=0.16.0; extra == "all"
Requires-Dist: tensorboard>=2.15.0; extra == "all"
